README
setup.py
metasort/__init__.py
metasort/cli.py
metasort/exceptions.py
metasort/sort.py
metasort/utils.py
metasort/webapp.py
metasort.egg-info/PKG-INFO
metasort.egg-info/SOURCES.txt
metasort.egg-info/dependency_links.txt
metasort.egg-info/entry_points.txt
metasort.egg-info/requires.txt
metasort.egg-info/top_level.txt