Metadata-Version: 1.0
Name: metasort
Version: 0.3.6.1
Summary: Filter reads based on taxonomy assignment from OneCodex.
Home-page: http://github.com/phelimb/metasort
Author: Phelim Bradley, Gil Goncalves
Author-email: wave@phel.im, lursty@gmail.com
License: MIT
Platform: UNKNOWN
